modelreport/_init_.py
modelreport/metric.py
modelreport-0.2.dist-info/LICENSE
modelreport-0.2.dist-info/METADATA
modelreport-0.2.dist-info/WHEEL
modelreport-0.2.dist-info/top_level.txt
modelreport-0.2.dist-info/RECORD
